example_package_zevt88/__init__.py
example_package_zevt88/example.py
typing_speed_zevt88-1.0.0.dist-info/LICENSE
typing_speed_zevt88-1.0.0.dist-info/METADATA
typing_speed_zevt88-1.0.0.dist-info/WHEEL
typing_speed_zevt88-1.0.0.dist-info/top_level.txt
typing_speed_zevt88-1.0.0.dist-info/RECORD
