Metadata-Version: 2.1
Name: typing-speed-zevt88
Version: 1.0.0
Summary: A package that allows running a typing speed test in the terminal
Author-email: zevt88 <zev.tovbin@gmail.com>
Project-URL: Homepage, https://github.com/ZevT88/typing-speed
Project-URL: Bug Tracker, https://github.com/ZevT88/typing-speed/issues
Classifier: Programming Language :: Python :: 3
Classifier: License :: OSI Approved :: MIT License
Classifier: Operating System :: OS Independent
Requires-Python: >=3
License-File: LICENSE
